delivery_person/__init__.py
delivery_person/detector.py
delivery_person-0.1.0.dist-info/METADATA
delivery_person-0.1.0.dist-info/WHEEL
delivery_person-0.1.0.dist-info/top_level.txt
delivery_person-0.1.0.dist-info/RECORD
