Metadata-Version: 2.1
Name: delivery-person
Version: 0.1.0
Summary: A package to detect delivery persons in images using a fine-tuned ResNet-50 model.
Home-page: https://github.com/issakafadil/delivery-person
Author: Faditech
Author-email: issakafadil@gmail.com
Classifier: Programming Language :: Python :: 3
Classifier: Operating System :: OS Independent
Requires-Python: >=3.6
Requires-Dist: torch >=1.7.1
Requires-Dist: torchvision >=0.8.2
Requires-Dist: Pillow >=8.0.1
Requires-Dist: numpy >=1.19.2
